brokerscore.py
brokerscore-0.1.3.dist-info/METADATA
brokerscore-0.1.3.dist-info/WHEEL
brokerscore-0.1.3.dist-info/RECORD
