Metadata-Version: 2.1
Name: brokerscore
Version: 0.1.3
Summary: Meso level network measure pbroker score as defined by Paquet-Clouston and Bouchard
Author: Guy
Author-email: guywiz@gmail.com
Requires-Python: >=3.10,<4.0
Classifier: Programming Language :: Python :: 3
Classifier: Programming Language :: Python :: 3.10
Classifier: Programming Language :: Python :: 3.11
Classifier: Programming Language :: Python :: 3.12
Requires-Dist: igraph (==0.10)
Requires-Dist: leidenalg (==0.10)
Requires-Dist: networkx (>=3.2.1,<4.0.0)
Requires-Dist: numpy (>=1.26,<2.0)
Requires-Dist: tulip-python (==5.7.2)
